markupfield/__init__.py
markupfield/fields.py
markupfield/markup.py
markupfield/widgets.py
markupfield/locale/de/LC_MESSAGES/django.mo
markupfield/locale/de/LC_MESSAGES/django.po
markupfield/tests/__init__.py
markupfield/tests/models.py
markupfield/tests/settings.py
markupfield/tests/tests.py
django_markupfield-2.0.1.dist-info/AUTHORS.txt
django_markupfield-2.0.1.dist-info/LICENSE
django_markupfield-2.0.1.dist-info/METADATA
django_markupfield-2.0.1.dist-info/WHEEL
django_markupfield-2.0.1.dist-info/top_level.txt
django_markupfield-2.0.1.dist-info/RECORD
