Metadata-Version: 2.1
Name: django-markupfield
Version: 2.0.1
Summary: Custom Django field for easy use of markup in text fields
Home-page: https://github.com/jamesturk/django-markupfield/
Author: James Turk
Author-email: dev@jamesturk.net
License: BSD License
Platform: any
Classifier: Development Status :: 5 - Production/Stable
Classifier: Intended Audience :: Developers
Classifier: License :: OSI Approved :: BSD License
Classifier: Natural Language :: English
Classifier: Operating System :: OS Independent
Classifier: Programming Language :: Python
Classifier: Programming Language :: Python :: 3
Classifier: Programming Language :: Python :: 3.6
Classifier: Programming Language :: Python :: 3.7
Classifier: Programming Language :: Python :: 3.8
Classifier: Programming Language :: Python :: 3.9
Classifier: Programming Language :: Python :: 3.10
Classifier: Environment :: Web Environment
